{
    "keep": {
        "days": false,
        "amount": 1000
    },
    "auditLog": "log/.4d2c4650549a9656b6d8247468d77039f47ba711-audit.json",
    "files": [
        {
            "date": 1638538482001,
            "name": "log/exception._2021-12-03",
            "hash": "2af27d703bdf994e2ec872f2cec96871"
        },
        {
            "date": 1638546007405,
            "name": "log/exception._2021-12-04",
            "hash": "8b2710f31dde97cf14ca6b3e4157b89b"
        },
        {
            "date": 1638778476555,
            "name": "log/exception._2021-12-06",
            "hash": "4ae18a2a7604560af5b6b1f916de230c"
        },
        {
            "date": 1639122449971,
            "name": "log/exception._2021-12-10",
            "hash": "f8cf7dd0d5e8067ef8a71ad572ae2a0f"
        },
        {
            "date": 1639918270344,
            "name": "log/exception._2021-12-19",
            "hash": "9d3cf70bf44575ed2fb2936cb1674f75"
        }
    ]
}